zzzero/__init__.py
zzzero/client.py
zzzero/const.py
zzzero/exceptions.py
zzzero/server.py
zzzero/util.py
zzzero-0.1.0.dist-info/METADATA
zzzero-0.1.0.dist-info/WHEEL
zzzero-0.1.0.dist-info/entry_points.txt
zzzero-0.1.0.dist-info/RECORD
